ppllocr/__init__.py
ppllocr/inference.py
ppllocr/assets/ppllocr_betav2.2.onnx
ppllocr-2.2.dist-info/licenses/LICENSE
ppllocr-2.2.dist-info/METADATA
ppllocr-2.2.dist-info/WHEEL
ppllocr-2.2.dist-info/top_level.txt
ppllocr-2.2.dist-info/RECORD
