Metadata-Version: 2.4
Name: ppllocr
Version: 2.2
Summary: High-performance Robust OCR powered
Author-email: Liveless <zhongxiaoma2027@gmail.com>
License: MIT
Project-URL: Homepage, https://github.com/gitpetyr/ppllocr
Project-URL: Bug Tracker, https://github.com/gitpetyr/ppllocr/issues
Requires-Python: >=3.10
License-File: LICENSE
Requires-Dist: numpy
Requires-Dist: opencv-python-headless
Requires-Dist: onnxruntime
Dynamic: license-file
